sbclient.py
sbclient-1.0.2.dist-info/METADATA
sbclient-1.0.2.dist-info/WHEEL
sbclient-1.0.2.dist-info/entry_points.txt
sbclient-1.0.2.dist-info/top_level.txt
sbclient-1.0.2.dist-info/RECORD
