Metadata-Version: 2.1
Name: sbclient
Version: 1.0.2
Summary: sbclient - CLI Splunkbase client
Home-page: UNKNOWN
Author: Hurricane Labs
Author-email: dev@hurricanelabs.com
License: UNKNOWN
Platform: UNKNOWN
Classifier: License :: OSI Approved :: MIT License
Classifier: Programming Language :: Python :: 2
Classifier: Programming Language :: Python :: 3
Classifier: Development Status :: 5 - Production/Stable
Requires-Dist: click
Requires-Dist: python-dateutil
Requires-Dist: defusedxml
Requires-Dist: lxml
Requires-Dist: requests
Requires-Dist: six (>=1.12.0)
